pubtools/__init__.py
pubtools/pluggy.py
pubtools/tracing.py
pubtools/_impl/__init__.py
pubtools/_impl/mallopt.py
pubtools/_impl/pluggy.py
pubtools/_impl/tracing.py
pubtools-1.4.3.dist-info/LICENSE
pubtools-1.4.3.dist-info/METADATA
pubtools-1.4.3.dist-info/WHEEL
pubtools-1.4.3.dist-info/entry_points.txt
pubtools-1.4.3.dist-info/top_level.txt
pubtools-1.4.3.dist-info/RECORD
