Metadata-Version: 2.1
Name: pubtools
Version: 1.4.3
Summary: Publishing tools project family
Home-page: https://github.com/release-engineering/pubtools
License: GNU General Public License
Project-URL: Documentation, https://release-engineering.github.io/pubtools/
Project-URL: Changelog, https://github.com/release-engineering/pubtools/blob/master/CHANGELOG.md
Classifier: Development Status :: 4 - Beta
Classifier: Intended Audience :: Developers
Classifier: License :: OSI Approved :: GNU General Public License v3 or later (GPLv3+)
Classifier: Programming Language :: Python :: 3
Classifier: Topic :: Software Development :: Libraries :: Python Modules
Requires-Python: >=3.6
License-File: LICENSE
Requires-Dist: pluggy
Requires-Dist: setuptools
Provides-Extra: tracing
Requires-Dist: opentelemetry-api; extra == "tracing"
Requires-Dist: opentelemetry-sdk; extra == "tracing"
